Metadata-Version: 1.1
Name: singlesp
Version: 1.0.1
Summary: Simple uses for Python subproccess module
Home-page: https://github.com/moisespsena/singlesp.py
Author: Moises P. Sena
Author-email: moisespsena@gmail.com
License: MIT
Keywords: system proc subprocess
Platform: UNKNOWN
Classifier: Development Status :: 5 - Production/Stable
Classifier: Topic :: Utilities
Classifier: Intended Audience :: Developers
Classifier: License :: OSI Approved :: MIT License
Classifier: Operating System :: OS Independent
Classifier: Programming Language :: Python :: 2
Classifier: Programming Language :: Python :: 2.7
Classifier: Programming Language :: Python :: 3
